keggtools/__init__.py
keggtools/_types.py
keggtools/_version.py
keggtools/analysis.py
keggtools/const.py
keggtools/models.py
keggtools/py.typed
keggtools/render.py
keggtools/resolver.py
keggtools/storage.py
keggtools/utils.py
keggtools/_static/msig_to_kegg_id.csv
keggtools-1.1.0.data/data/msig_to_kegg_id.csv
keggtools-1.1.0.dist-info/licenses/LICENSE
keggtools-1.1.0.dist-info/WHEEL
keggtools-1.1.0.dist-info/METADATA
keggtools-1.1.0.dist-info/RECORD
