Metadata-Version: 2.4
Name: keggtools
Version: 1.1.0
Summary: Enrichment analysis and visualisation toolkit for KEGG pathways
Author-email: harryhaller001 <harryhaller001@gmail.com>
Maintainer-email: harryhaller001 <harryhaller001@gmail.com>
Requires-Python: >=3.10
Classifier: Development Status :: 3 - Alpha
Classifier: Intended Audience :: Healthcare Industry
Classifier: Intended Audience :: Science/Research
Classifier: License :: OSI Approved :: MIT License
Classifier: Natural Language :: English
Classifier: Operating System :: OS Independent
Classifier: Programming Language :: Python :: 3 :: Only
Classifier: Programming Language :: Python :: 3.10
Classifier: Programming Language :: Python :: 3.11
Classifier: Programming Language :: Python :: 3.12
Classifier: Typing :: Typed
License-File: LICENSE
Requires-Dist: matplotlib
Requires-Dist: pandas
Requires-Dist: pillow
Requires-Dist: pybiomart
Requires-Dist: pydantic-xml
Requires-Dist: pydot
Requires-Dist: requests
Requires-Dist: scipy
Requires-Dist: ipython ; extra == "docs"
Requires-Dist: nbsphinx ; extra == "docs"
Requires-Dist: sphinx ; extra == "docs"
Requires-Dist: sphinx-autoapi ; extra == "docs"
Requires-Dist: sphinx-autodoc-typehints ; extra == "docs"
Requires-Dist: sphinx-book-theme ; extra == "docs"
Requires-Dist: coverage ; extra == "test"
Requires-Dist: flit ; extra == "test"
Requires-Dist: ipykernel ; extra == "test"
Requires-Dist: ipython ; extra == "test"
Requires-Dist: ipywidgets ; extra == "test"
Requires-Dist: isort ; extra == "test"
Requires-Dist: mypy ; extra == "test"
Requires-Dist: pandas-stubs ; extra == "test"
Requires-Dist: pytest ; extra == "test"
Requires-Dist: responses ; extra == "test"
Requires-Dist: ruff ; extra == "test"
Requires-Dist: setuptools ; extra == "test"
Requires-Dist: twine ; extra == "test"
Requires-Dist: types-requests ; extra == "test"
Project-URL: Documentation, https://keggtools.org/
Project-URL: Homepage, https://github.com/harryhaller001/keggtools
Project-URL: Source, https://github.com/harryhaller001/keggtools
Provides-Extra: docs
Provides-Extra: test
